telemetry/__init__.py
telemetry/telemetry_client.py
telemetry/telemetry_logger.py
telemetry/telemetry_mqtt.py
telemetry/telemetry_mqtt_server.py
telemetry/telemetry_server.py
telemetry/telemetry_socket_server.py
telemetry/telemetry_storage.py
telemetry/telemetry_stream.py
pyros_telemetry-1.0.1.dist-info/LICENSE
pyros_telemetry-1.0.1.dist-info/METADATA
pyros_telemetry-1.0.1.dist-info/WHEEL
pyros_telemetry-1.0.1.dist-info/top_level.txt
pyros_telemetry-1.0.1.dist-info/RECORD
