Metadata-Version: 2.1
Name: pyros-telemetry
Version: 1.0.1
Summary: Telemetry package aimed for PyROS
Home-page: https://github.com/Abstract-Horizon/pyros-telemetry
Author: Daniel Sendula
License: UNKNOWN
Platform: UNKNOWN
Classifier: Programming Language :: Python :: 3
Classifier: License :: OSI Approved :: Apache Software License
Classifier: Operating System :: OS Independent
Requires-Python: >=3.6
License-File: LICENSE
